awesome_tatsu_math/__init__.py
awesome_tatsu_math/core.py
tests/test_core.py
awesome_tatsu_math-0.1.2.dist-info/METADATA
awesome_tatsu_math-0.1.2.dist-info/WHEEL
awesome_tatsu_math-0.1.2.dist-info/top_level.txt
awesome_tatsu_math-0.1.2.dist-info/RECORD
