Metadata-Version: 2.4
Name: awesome-tatsu-math
Version: 0.1.2
Summary: A tiny example math library
Author-email: Tatsuhiro Shimizu <t.miyazaki3831@gmail.com>
License: MIT
Requires-Python: >=3.9
Requires-Dist: build>=1.3.0
Requires-Dist: twine>=6.2.0
